pyftml-0.1.3.dist-info/METADATA
pyftml-0.1.3.dist-info/WHEEL
pyftml/__init__.py
pyftml/pyftml.cp39-win32.pyd
pyftml-0.1.3.dist-info/RECORD
