Metadata-Version: 2.1
Name: pyftml
Version: 0.1.3
Summary: Python bindings for ftml
Keywords: ftml,scp,wikidot
Author: MrNereof <mrnereof@gmail.com>
Author-email: MrNereof <mrnereof@gmail.com>
License: MIT
Project-URL: Source Code, https://github.com/skippy-dev/pyftml
